{"name": "cvrp-0-al-3", "region": "al-0", "origin": {"lng": -35.75241110396336, "lat": -9.567428230515462}, "vehicle_capacity": 110, "deliveries": [{"id": "6de712ba78b183b2d4ea29a1a5494112", "point": {"lng": -35.78326886052082, "lat": -9.566888907552952}, "size": 10, "preparation": 11, "time": 42, "timestamp": 150}, {"id": "6d1c3ff3378639cd04f5d9510ab559cd", "point": {"lng": -35.7859168396538, "lat": -9.566909606998436}, "size": 7, "preparation": 4, "time": 43, "timestamp": 143}, {"id": "aea5c7ad556f104b13ebed8f625f1cb3", "point": {"lng": -35.78436406236529, "lat": -9.567758633580526}, "size": 9, "preparation": 11, "time": 30, "timestamp": 11}, {"id": "51a46b38a54f4cf572ee91fdae8f3771", "point": {"lng": -35.72705447229705, "lat": -9.557191255801191}, "size": 7, "preparation": 13, "time": 28, "timestamp": 157}, {"id": "4ca7ab84c5234784eb42e00d8b78a234", "point": {"lng": -35.78001961486848, "lat": -9.581223984910789}, "size": 3, "preparation": 6, "time": 40, "timestamp": 186}, {"id": "c3b87f83d8b2ee9c8a89fda5284bf90c", "point": {"lng": -35.781768069150644, "lat": -9.582692307406523}, "size": 10, "preparation": 4, "time": 41, "timestamp": 118}, {"id": "db42f36c1c37ca92b073bf235a8ca35b", "point": {"lng": -35.78044793357857, "lat": -9.584952179663702}, "size": 4, "preparation": 10, "time": 27, "timestamp": 149}, {"id": "4c994c1d63ed9550c176282020adadc0", "point": {"lng": -35.780944677420315, "lat": -9.581273461111286}, "size": 9, "preparation": 5, "time": 38, "timestamp": 211}, {"id": "371f17fc2455becda6f3566a7686f30a", "point": {"lng": -35.77928963489967, "lat": -9.585575770945264}, "size": 6, "preparation": 6, "time": 30, "timestamp": 246}, {"id": "7b2a9bf37206c32636c6b0e5f4073cd4", "point": {"lng": -35.79420793956344, "lat": -9.53766363660151}, "size": 3, "preparation": 7, "time": 33, "timestamp": 159}, {"id": "703132a1b0fe3ee0ca645ac5837a8bb5", "point": {"lng": -35.7913211335206, "lat": -9.543531526187234}, "size": 5, "preparation": 8, "time": 34, "timestamp": 266}, {"id": "dbab5847625aca2397be56bf9d1909a", "point": {"lng": -35.79297847399036, "lat": -9.540919259316956}, "size": 4, "preparation": 13, "time": 33, "timestamp": 205}, {"id": "7330a2a3d42bfd5fad3db03c722d166f", "point": {"lng": -35.79138330629895, "lat": -9.543030235880135}, "size": 3, "preparation": 7, "time": 50, "timestamp": 98}, {"id": "b557f6de5de5ba48d111134dfdd037cc", "point": {"lng": -35.79060101215854, "lat": -9.542461127525877}, "size": 6, "preparation": 7, "time": 39, "timestamp": 268}, {"id": "9f09ddde0dda96a34fed0dcb306e5574", "point": {"lng": -35.79199579222637, "lat": -9.545368553261254}, "size": 3, "preparation": 2, "time": 45, "timestamp": 286}, {"id": "f6c1bba310a9edc113b403648c99db64", "point": {"lng": -35.76389000152574, "lat": -9.592743323500574}, "size": 9, "preparation": 11, "time": 44, "timestamp": 355}, {"id": "5b0758af5886584c948a041ac25acc50", "point": {"lng": -35.7668645558283, "lat": -9.596958886238374}, "size": 9, "preparation": 6, "time": 36, "timestamp": 69}, {"id": "d435242351f89ff5e151c5801ac7eda", "point": {"lng": -35.76379210058035, "lat": -9.597859257410592}, "size": 7, "preparation": 4, "time": 39, "timestamp": 303}, {"id": "8acc42dba0836fd6192df22a56f9d50", "point": {"lng": -35.76677821463592, "lat": -9.592357975477919}, "size": 4, "preparation": 10, "time": 22, "timestamp": 54}, {"id": "f81c201417c94f50b7737c509a2c1812", "point": {"lng": -35.77022080964339, "lat": -9.544455603666142}, "size": 3, "preparation": 5, "time": 48, "timestamp": 247}, {"id": "cb148ba84bb0e00446688b1006c27a03", "point": {"lng": -35.77024757617341, "lat": -9.542349079076917}, "size": 7, "preparation": 6, "time": 37, "timestamp": 204}, {"id": "908878eb4a4cd379fb13db89bb40027a", "point": {"lng": -35.76739157294493, "lat": -9.545741843574685}, "size": 3, "preparation": 15, "time": 34, "timestamp": 244}, {"id": "c587507f2695e1cd07c1a4b0964da4da", "point": {"lng": -35.768995254836426, "lat": -9.544603422625853}, "size": 10, "preparation": 4, "time": 39, "timestamp": 19}, {"id": "c595a09db63b63c155e50d29c5056e98", "point": {"lng": -35.750348110374375, "lat": -9.550163434688805}, "size": 2, "preparation": 11, "time": 43, "timestamp": 46}, {"id": "8df5689715597eb72581532d1c15eed5", "point": {"lng": -35.747631813434126, "lat": -9.552052294035182}, "size": 3, "preparation": 7, "time": 35, "timestamp": 310}, {"id": "a077af7242867eafac68a32e8a008408", "point": {"lng": -35.7481900251793, "lat": -9.555648391872621}, "size": 5, "preparation": 3, "time": 42, "timestamp": 154}, {"id": "c4d303b91adce39ae1394ae5fe01146", "point": {"lng": -35.746374802364755, "lat": -9.55444096565533}, "size": 3, "preparation": 8, "time": 48, "timestamp": 242}, {"id": "a7e54c1b0776aa0c9c99f455f65c7087", "point": {"lng": -35.74773131362322, "lat": -9.546423513210428}, "size": 8, "preparation": 14, "time": 49, "timestamp": 282}, {"id": "c5624d3401e4c2df50e00fc4d62a73f0", "point": {"lng": -35.74785455324699, "lat": -9.549153338932626}, "size": 10, "preparation": 5, "time": 43, "timestamp": 177}, {"id": "7b8362479eec858865a2b7b15271acad", "point": {"lng": -35.747209763664934, "lat": -9.55061849116079}, "size": 8, "preparation": 2, "time": 22, "timestamp": 309}, {"id": "6e4506c17f263fbd8e7f7ce0e54ae011", "point": {"lng": -35.749247795335755, "lat": -9.549500189237373}, "size": 3, "preparation": 6, "time": 28, "timestamp": 242}, {"id": "874d35eb74c37503fac484e09da58af3", "point": {"lng": -35.747382766628455, "lat": -9.54594272998335}, "size": 3, "preparation": 11, "time": 41, "timestamp": 86}, {"id": "5d41d00844148ad339720f1dba612c45", "point": {"lng": -35.74861149012282, "lat": -9.548182581463214}, "size": 8, "preparation": 9, "time": 27, "timestamp": 328}, {"id": "6e4506c17f263fbd8e7f7ce0e54ae011", "point": {"lng": -35.749247795335755, "lat": -9.549500189237373}, "size": 3, "preparation": 6, "time": 28, "timestamp": 242}, {"id": "974a7dacfcd2cccffde847518ecbfcef", "point": {"lng": -35.74621937510562, "lat": -9.552955507445665}, "size": 6, "preparation": 7, "time": 48, "timestamp": 248}, {"id": "e6966d2a22d15eb15f23c7358e4a20f5", "point": {"lng": -35.73969587754637, "lat": -9.569172040800709}, "size": 7, "preparation": 9, "time": 42, "timestamp": 241}, {"id": "2c92b007847598f7584aaf4253819646", "point": {"lng": -35.73662688553782, "lat": -9.562550232631768}, "size": 7, "preparation": 8, "time": 49, "timestamp": 200}, {"id": "ce3ef8b9e3d097c0dc653077c7eb21b1", "point": {"lng": -35.73822664184544, "lat": -9.560736909167233}, "size": 10, "preparation": 5, "time": 33, "timestamp": 353}, {"id": "e52e2eaea8f767487851192d724a96e0", "point": {"lng": -35.73426770316494, "lat": -9.590354478667194}, "size": 3, "preparation": 5, "time": 46, "timestamp": 85}, {"id": "fd932af7f549d1d82e97d430efa349c3", "point": {"lng": -35.7376748957962, "lat": -9.589607435613928}, "size": 1, "preparation": 9, "time": 28, "timestamp": 228}, {"id": "cba7ac23630bd22af62b756fd6653c71", "point": {"lng": -35.73876575751123, "lat": -9.592505358911243}, "size": 2, "preparation": 13, "time": 24, "timestamp": 120}, {"id": "57c899d0c7e7060afa0439e1d14b9de3", "point": {"lng": -35.73636808364132, "lat": -9.592832726537214}, "size": 9, "preparation": 11, "time": 30, "timestamp": 64}, {"id": "80b7975b3f343ef3af582bd269cd27ab", "point": {"lng": -35.723213803996046, "lat": -9.537441737134209}, "size": 10, "preparation": 13, "time": 44, "timestamp": 247}, {"id": "f147f472ce7d79bb2833d71ad7d76b3f", "point": {"lng": -35.72377538250207, "lat": -9.538542586364505}, "size": 6, "preparation": 15, "time": 43, "timestamp": 30}, {"id": "acb2b8718df7a62daded9e6485a0b56d", "point": {"lng": -35.71538489540467, "lat": -9.53771384412184}, "size": 8, "preparation": 5, "time": 42, "timestamp": 172}, {"id": "71a629a0e1a7aaa424c82be7859ed884", "point": {"lng": -35.71136833683621, "lat": -9.569137307512174}, "size": 5, "preparation": 10, "time": 34, "timestamp": 67}, {"id": "c8c9412df305a2fbcbfe030860a82a02", "point": {"lng": -35.71358451177332, "lat": -9.570217127759273}, "size": 1, "preparation": 5, "time": 43, "timestamp": 169}, {"id": "67206fcdec46afbcb260b217867d4292", "point": {"lng": -35.72185582929323, "lat": -9.5413252862761}, "size": 6, "preparation": 6, "time": 41, "timestamp": 8}, {"id": "7256816b45bff2a1fae47b1db79b683f", "point": {"lng": -35.72149975652121, "lat": -9.539740889175745}, "size": 10, "preparation": 12, "time": 46, "timestamp": 1}, {"id": "9b87e739b8cfdeb65981a8c58e4524c0", "point": {"lng": -35.718707979956775, "lat": -9.541979223074112}, "size": 9, "preparation": 10, "time": 48, "timestamp": 355}, {"id": "22ac24785e2db09e04ca60714076c325", "point": {"lng": -35.72252279460738, "lat": -9.544200657261788}, "size": 7, "preparation": 4, "time": 51, "timestamp": 213}, {"id": "ccddee781c0ead5e35b7c93b58831d41", "point": {"lng": -35.72257224653055, "lat": -9.542238521291393}, "size": 8, "preparation": 2, "time": 43, "timestamp": 297}, {"id": "a2fe89b64cf2b828b4510cdf29b02ac1", "point": {"lng": -35.71917962793044, "lat": -9.540680084666732}, "size": 3, "preparation": 7, "time": 43, "timestamp": 281}, {"id": "3b113c49381fa4ee06045df1fce1f1eb", "point": {"lng": -35.71835548737371, "lat": -9.542215279871083}, "size": 1, "preparation": 4, "time": 27, "timestamp": 335}, {"id": "a2fe89b64cf2b828b4510cdf29b02ac1", "point": {"lng": -35.71917962793044, "lat": -9.540680084666732}, "size": 3, "preparation": 7, "time": 43, "timestamp": 281}, {"id": "6b2a64df741284ee11f835ad161a08c8", "point": {"lng": -35.76726390444905, "lat": -9.57529096805649}, "size": 10, "preparation": 15, "time": 36, "timestamp": 77}, {"id": "addf61b7ff3d9f6ca7b4f3782ebec1c9", "point": {"lng": -35.76614966071789, "lat": -9.573957212123256}, "size": 2, "preparation": 6, "time": 25, "timestamp": 10}, {"id": "387160c0f7434ad4d6b606f8c7bd0a30", "point": {"lng": -35.78667239988538, "lat": -9.556626238560632}, "size": 6, "preparation": 3, "time": 39, "timestamp": 41}, {"id": "2c0c46e60d11a0e89e5c191be5a0d780", "point": {"lng": -35.78468076374658, "lat": -9.556308045558565}, "size": 1, "preparation": 11, "time": 37, "timestamp": 314}, {"id": "38afa2a1556afcf12bef86c717dace92", "point": {"lng": -35.738103527914284, "lat": -9.55770093995015}, "size": 4, "preparation": 13, "time": 23, "timestamp": 150}, {"id": "8e35c319ed8990834ebb14ed62084dcb", "point": {"lng": -35.73662238742457, "lat": -9.55388800155403}, "size": 6, "preparation": 15, "time": 38, "timestamp": 318}, {"id": "a5e283b2343d16373482fd146046eefe", "point": {"lng": -35.76900600771904, "lat": -9.572804088086325}, "size": 4, "preparation": 12, "time": 39, "timestamp": 171}, {"id": "299bca1f4fac92692eecbc772ad277b0", "point": {"lng": -35.751115007229316, "lat": -9.56178074734983}, "size": 5, "preparation": 2, "time": 45, "timestamp": 85}, {"id": "277e13783af1dc862f45f5fbe8a3eaf1", "point": {"lng": -35.749463287156495, "lat": -9.556847383201605}, "size": 9, "preparation": 4, "time": 32, "timestamp": 70}, {"id": "e437503ea9002c4d3bfd82a3e4664b19", "point": {"lng": -35.781995713506504, "lat": -9.572529235493457}, "size": 1, "preparation": 10, "time": 40, "timestamp": 348}, {"id": "11cceff3775962e58ed7042a41f23265", "point": {"lng": -35.78138811016131, "lat": -9.572338418040681}, "size": 2, "preparation": 13, "time": 48, "timestamp": 175}, {"id": "1a4f8adc480afbd665ff90a4cc5010dc", "point": {"lng": -35.77956419544989, "lat": -9.57408674995161}, "size": 7, "preparation": 14, "time": 45, "timestamp": 2}, {"id": "dd88293bbf788bf4e8fdf54c66b6f84d", "point": {"lng": -35.75000491840731, "lat": -9.546475554323756}, "size": 9, "preparation": 4, "time": 35, "timestamp": 14}, {"id": "58af04e8af7649456fc10345be5d4790", "point": {"lng": -35.75334503268999, "lat": -9.54206718748137}, "size": 9, "preparation": 12, "time": 36, "timestamp": 167}, {"id": "48a6b91cd1e981f1132bb282d322ef0a", "point": {"lng": -35.77099879254061, "lat": -9.593718597484266}, "size": 6, "preparation": 7, "time": 39, "timestamp": 193}, {"id": "cedb05c8b5ed0e2e3d783744930107ee", "point": {"lng": -35.77257619764483, "lat": -9.590481491148076}, "size": 1, "preparation": 14, "time": 52, "timestamp": 299}, {"id": "80a0300a0acedb9b7f2730939fcc42bb", "point": {"lng": -35.772737274785676, "lat": -9.592410174864952}, "size": 6, "preparation": 10, "time": 35, "timestamp": 283}, {"id": "b136cb877bb3f8f8fe24cb12b9f18f5e", "point": {"lng": -35.772323392559336, "lat": -9.590936769300445}, "size": 9, "preparation": 2, "time": 25, "timestamp": 231}, {"id": "e680bfb299fc2167471fe169c468e186", "point": {"lng": -35.773178460838714, "lat": -9.59211012370016}, "size": 1, "preparation": 12, "time": 33, "timestamp": 236}, {"id": "32e5e600609aac95f649f9f8d18ed1f", "point": {"lng": -35.76978938688593, "lat": -9.592046831231333}, "size": 10, "preparation": 8, "time": 48, "timestamp": 12}, {"id": "ef5552f4ecd060182362d2e85eb45f8b", "point": {"lng": -35.77581389812426, "lat": -9.590559116010201}, "size": 3, "preparation": 3, "time": 42, "timestamp": 18}, {"id": "f561404f0cf9a814e7425a6c50846af8", "point": {"lng": -35.772880852105025, "lat": -9.591191154660093}, "size": 8, "preparation": 3, "time": 45, "timestamp": 302}, {"id": "79ff0a8584573456ea5e36065486c0cd", "point": {"lng": -35.77359301494025, "lat": -9.592534220447916}, "size": 2, "preparation": 11, "time": 22, "timestamp": 37}, {"id": "2ca005ca0f6694a20e1f6ccf00ec6e4f", "point": {"lng": -35.770768439298685, "lat": -9.589233494054357}, "size": 7, "preparation": 15, "time": 47, "timestamp": 203}, {"id": "bd51a60cccf1c88d9cd74a3e1fdcd027", "point": {"lng": -35.76953624852098, "lat": -9.592666563099613}, "size": 3, "preparation": 15, "time": 26, "timestamp": 144}, {"id": "fb12757810086cefe1ae2e214281ef67", "point": {"lng": -35.79413304356927, "lat": -9.576621514457875}, "size": 9, "preparation": 5, "time": 50, "timestamp": 352}, {"id": "ca8286dca0567257454d4d486a67aa5c", "point": {"lng": -35.79042142331411, "lat": -9.580954158644753}, "size": 4, "preparation": 9, "time": 42, "timestamp": 313}, {"id": "7742a2d1abfe9d6f5fba984f86fdcf21", "point": {"lng": -35.70257566114436, "lat": -9.585249337752904}, "size": 7, "preparation": 5, "time": 34, "timestamp": 52}, {"id": "7afa1ceda54ac13655f8e76548511310", "point": {"lng": -35.7446330372702, "lat": -9.596348191471188}, "size": 10, "preparation": 12, "time": 26, "timestamp": 301}, {"id": "8cd651e8c9a298333b71d52e1f772be3", "point": {"lng": -35.7409739793694, "lat": -9.590391047365406}, "size": 9, "preparation": 1, "time": 23, "timestamp": 283}, {"id": "d87b37ce4d98866ddbac1639727482cd", "point": {"lng": -35.74128880244473, "lat": -9.593164070675462}, "size": 4, "preparation": 11, "time": 42, "timestamp": 188}, {"id": "da6b67e4d9ff68843a19b7749775063", "point": {"lng": -35.74196604253684, "lat": -9.589451484995866}, "size": 7, "preparation": 6, "time": 25, "timestamp": 314}, {"id": "3768fbfa19c70facba8eebec5da4cf88", "point": {"lng": -35.78544994116776, "lat": -9.53519333109763}, "size": 1, "preparation": 8, "time": 41, "timestamp": 285}, {"id": "50fca57cc9618d0a363335678ef5871a", "point": {"lng": -35.78161650860159, "lat": -9.544578761659047}, "size": 2, "preparation": 14, "time": 26, "timestamp": 56}, {"id": "60212f48fe147ea7654444be443cc69d", "point": {"lng": -35.77922794846048, "lat": -9.543380470938581}, "size": 5, "preparation": 4, "time": 41, "timestamp": 293}, {"id": "e73e1b7161d15d20d7d778a0c9b452eb", "point": {"lng": -35.78141971420123, "lat": -9.542572180155343}, "size": 7, "preparation": 10, "time": 44, "timestamp": 122}, {"id": "672828253b69170b306ddc04c4d58a26", "point": {"lng": -35.78965541497375, "lat": -9.570348210535204}, "size": 2, "preparation": 7, "time": 48, "timestamp": 359}, {"id": "50b07876380be251c958384e15e3b147", "point": {"lng": -35.788379890112864, "lat": -9.568963822358421}, "size": 8, "preparation": 10, "time": 50, "timestamp": 203}, {"id": "e6c5689ac138de54a00f23be0e6e5866", "point": {"lng": -35.78775968087891, "lat": -9.570022924613811}, "size": 8, "preparation": 3, "time": 34, "timestamp": 181}, {"id": "ff3f1b799e8c40ae2cea3333022d05c", "point": {"lng": -35.78992241717786, "lat": -9.566995261989529}, "size": 7, "preparation": 11, "time": 41, "timestamp": 191}, {"id": "573a533d186bc2716538eaf0b534af65", "point": {"lng": -35.79683863581102, "lat": -9.561331810664662}, "size": 8, "preparation": 2, "time": 28, "timestamp": 28}, {"id": "7fd69338efa35e2008fa7bcbc4330939", "point": {"lng": -35.78894657126827, "lat": -9.571141984945049}, "size": 9, "preparation": 7, "time": 42, "timestamp": 135}, {"id": "45f365d95dab8c677595be78ad67308e", "point": {"lng": -35.79096129565144, "lat": -9.569296552363578}, "size": 1, "preparation": 2, "time": 47, "timestamp": 319}, {"id": "b3b9a2605a005039710c1f2609de9f6", "point": {"lng": -35.76078981834562, "lat": -9.561666744462293}, "size": 1, "preparation": 3, "time": 41, "timestamp": 103}, {"id": "4ec28e2bcceb86b289a72e86779e195b", "point": {"lng": -35.74829303634072, "lat": -9.569743479456815}, "size": 9, "preparation": 3, "time": 38, "timestamp": 5}, {"id": "3fcfc1b76f66541cd65553c3566aab3a", "point": {"lng": -35.7653663004241, "lat": -9.583186584158808}, "size": 7, "preparation": 7, "time": 24, "timestamp": 240}, {"id": "3d398141a807e381f03b5f2344972379", "point": {"lng": -35.766777059254004, "lat": -9.585173290428322}, "size": 1, "preparation": 14, "time": 34, "timestamp": 194}, {"id": "bcc4b5718b80fc07ee48510f23208d64", "point": {"lng": -35.76433794530161, "lat": -9.584391696487645}, "size": 3, "preparation": 8, "time": 26, "timestamp": 191}, {"id": "243bfa2a0259afa5e7d3122bb9a9bf29", "point": {"lng": -35.77422004623953, "lat": -9.582606818833584}, "size": 9, "preparation": 1, "time": 34, "timestamp": 103}, {"id": "ea65bd3abb0dc9323a40220bac976170", "point": {"lng": -35.7721808821533, "lat": -9.58365355991778}, "size": 9, "preparation": 13, "time": 29, "timestamp": 120}, {"id": "6653e512a2efa549425594099e6ddc76", "point": {"lng": -35.77314298465531, "lat": -9.582855822807636}, "size": 9, "preparation": 4, "time": 35, "timestamp": 168}, {"id": "b37913839fe047ca5a92e0b5e990b3d2", "point": {"lng": -35.72397705054891, "lat": -9.560354893240625}, "size": 4, "preparation": 15, "time": 27, "timestamp": 236}, {"id": "a3b14a077cd54437e07158a1519b6383", "point": {"lng": -35.721789299059594, "lat": -9.563979275128064}, "size": 8, "preparation": 6, "time": 37, "timestamp": 152}, {"id": "c96f8791d3bd973c223cdad3876054a6", "point": {"lng": -35.72210755305268, "lat": -9.558519376587313}, "size": 1, "preparation": 8, "time": 43, "timestamp": 88}, {"id": "3f90985e097e738e84f590fb41168f93", "point": {"lng": -35.76741546136289, "lat": -9.564209608065994}, "size": 1, "preparation": 10, "time": 22, "timestamp": 329}, {"id": "c7c3de62e9ef38a51d02e7caf52323f3", "point": {"lng": -35.78751911276316, "lat": -9.58706313749979}, "size": 7, "preparation": 5, "time": 45, "timestamp": 83}, {"id": "1a3df646bcbf06e28faf3688db2def40", "point": {"lng": -35.78903672779808, "lat": -9.583063238628734}, "size": 3, "preparation": 8, "time": 29, "timestamp": 258}, {"id": "93e04cf6ee0e51b6387686d0d911b6f6", "point": {"lng": -35.78887405701287, "lat": -9.587778939002169}, "size": 1, "preparation": 12, "time": 48, "timestamp": 42}, {"id": "4d5cda4d2034543ff8a2b69e27e2d5b4", "point": {"lng": -35.7907731313871, "lat": -9.586606614745685}, "size": 5, "preparation": 2, "time": 37, "timestamp": 351}, {"id": "405b32b76632ff867b5a67e8bcf35028", "point": {"lng": -35.75151834605326, "lat": -9.534219030769275}, "size": 5, "preparation": 10, "time": 23, "timestamp": 2}, {"id": "ba6ea04a593a441aabdc6dd2277a73c9", "point": {"lng": -35.75664594445586, "lat": -9.573864015985054}, "size": 6, "preparation": 1, "time": 23, "timestamp": 205}, {"id": "7f407a8cdfef27fbf25e2340315ddf86", "point": {"lng": -35.756289278802896, "lat": -9.57454816635825}, "size": 1, "preparation": 1, "time": 49, "timestamp": 274}, {"id": "6e81bc6fef0d01bc11bda8c962e3bb86", "point": {"lng": -35.75621829524159, "lat": -9.576441421552666}, "size": 7, "preparation": 15, "time": 51, "timestamp": 212}, {"id": "fd52463c1e723b9959422b8608938213", "point": {"lng": -35.75462484886763, "lat": -9.574690270875701}, "size": 9, "preparation": 13, "time": 49, "timestamp": 22}, {"id": "e9194882ab39e21708142f84c5091608", "point": {"lng": -35.75471484447153, "lat": -9.575576643735577}, "size": 4, "preparation": 2, "time": 42, "timestamp": 197}, {"id": "b4cb2b0b41b529c63076282f0b7467a9", "point": {"lng": -35.68016513030975, "lat": -9.532262241433488}, "size": 2, "preparation": 6, "time": 45, "timestamp": 48}, {"id": "8d74a01d682a78365514e4131768f22a", "point": {"lng": -35.72941593453446, "lat": -9.552182533926098}, "size": 5, "preparation": 14, "time": 42, "timestamp": 322}, {"id": "be7df0cd8f0698e7e31e6208dec9d17a", "point": {"lng": -35.73149447167223, "lat": -9.552052963506842}, "size": 8, "preparation": 10, "time": 22, "timestamp": 360}, {"id": "1d8696595e8097806ff32eacb7fc1c41", "point": {"lng": -35.72815582548144, "lat": -9.547982045624243}, "size": 4, "preparation": 1, "time": 31, "timestamp": 197}, {"id": "65157e0cbce7a8f94ca37e6f19e42810", "point": {"lng": -35.734682246789475, "lat": -9.549591084480506}, "size": 8, "preparation": 5, "time": 42, "timestamp": 49}, {"id": "31360a350f7fda08acc3fef0e5b6e9cc", "point": {"lng": -35.760849116755566, "lat": -9.585210894332569}, "size": 1, "preparation": 8, "time": 31, "timestamp": 25}, {"id": "480b0381110a2d3265919b53c2107475", "point": {"lng": -35.75741994987665, "lat": -9.586454891536416}, "size": 5, "preparation": 13, "time": 41, "timestamp": 152}, {"id": "10c6c7bca89928865eee560a795010d2", "point": {"lng": -35.759873302030094, "lat": -9.589378992607106}, "size": 5, "preparation": 11, "time": 48, "timestamp": 183}, {"id": "8a3f1e07f93c0f1f7381740a14a46ae0", "point": {"lng": -35.72708035167411, "lat": -9.590745564895974}, "size": 2, "preparation": 9, "time": 47, "timestamp": 175}, {"id": "2ac289dd1f2ea8616d23bf45fb02d3b", "point": {"lng": -35.73115430184411, "lat": -9.588578490756023}, "size": 6, "preparation": 10, "time": 39, "timestamp": 353}, {"id": "fdf6d718c8fcf2a9027a66f8f4329419", "point": {"lng": -35.72735983271804, "lat": -9.588828616772698}, "size": 8, "preparation": 6, "time": 24, "timestamp": 304}, {"id": "6f5f2919008e3eecf62c1c2b333d7d00", "point": {"lng": -35.74985669848312, "lat": -9.566428368121057}, "size": 3, "preparation": 1, "time": 35, "timestamp": 252}, {"id": "69de3160cbc87094e1f24113d4f3ed18", "point": {"lng": -35.751049543703736, "lat": -9.566769914091912}, "size": 4, "preparation": 14, "time": 25, "timestamp": 280}, {"id": "f03ad601b4158b90533364a073ea404e", "point": {"lng": -35.75314381706978, "lat": -9.566321988099505}, "size": 2, "preparation": 12, "time": 44, "timestamp": 212}, {"id": "3fd6943b2c5e46db4af77a5235e02482", "point": {"lng": -35.74939862816202, "lat": -9.567055954613947}, "size": 2, "preparation": 14, "time": 29, "timestamp": 2}, {"id": "5c82c6517c001f807d192c97fc213089", "point": {"lng": -35.75362025493963, "lat": -9.567852550937648}, "size": 9, "preparation": 4, "time": 36, "timestamp": 220}, {"id": "2c56ddae05b95d1a0fc6fcfdd8c8c9ae", "point": {"lng": -35.774961651296444, "lat": -9.587208461441273}, "size": 4, "preparation": 10, "time": 40, "timestamp": 147}, {"id": "6b7962d0b1076515727c0acb258edaa0", "point": {"lng": -35.777069432842694, "lat": -9.58724936237913}, "size": 2, "preparation": 11, "time": 24, "timestamp": 43}, {"id": "3adbb395da3678dd7be111dbbae753f8", "point": {"lng": -35.77247928038188, "lat": -9.58510693738556}, "size": 8, "preparation": 3, "time": 32, "timestamp": 225}, {"id": "443fcc7da2e3436d1f78cb0b7fa8f549", "point": {"lng": -35.70159030010123, "lat": -9.565645371385523}, "size": 4, "preparation": 10, "time": 23, "timestamp": 152}, {"id": "2676960896e081bd97f0f23286b03e57", "point": {"lng": -35.76166586731577, "lat": -9.59606128270187}, "size": 2, "preparation": 14, "time": 37, "timestamp": 214}, {"id": "31e6bbb4392e860572de49ece84cfd89", "point": {"lng": -35.786160275930555, "lat": -9.553176466519712}, "size": 9, "preparation": 10, "time": 25, "timestamp": 61}, {"id": "ef35be7f8721e06a3b791bd118d4836b", "point": {"lng": -35.788799979055916, "lat": -9.555485067709856}, "size": 5, "preparation": 10, "time": 24, "timestamp": 96}, {"id": "bee34055e1a1da142df6a797729e45db", "point": {"lng": -35.785095612607755, "lat": -9.553089449012015}, "size": 10, "preparation": 10, "time": 50, "timestamp": 154}, {"id": "9af1cad868fca80c39b2a83aaaeb26b7", "point": {"lng": -35.758716728663885, "lat": -9.567772230221353}, "size": 2, "preparation": 12, "time": 43, "timestamp": 355}, {"id": "701d2e4ea397031963b7b4e38bf46a78", "point": {"lng": -35.75191919970082, "lat": -9.587312366267039}, "size": 5, "preparation": 11, "time": 26, "timestamp": 349}, {"id": "9bae32688bcbfebd6bcb6eabb5391122", "point": {"lng": -35.74825065212524, "lat": -9.589227270111797}, "size": 10, "preparation": 1, "time": 45, "timestamp": 262}, {"id": "a5c03ab7eb1587e0773b0651725fc037", "point": {"lng": -35.80416959842295, "lat": -9.562379565098603}, "size": 5, "preparation": 8, "time": 24, "timestamp": 347}, {"id": "2b86541f57cd3a516cd2b2860bfd6a7c", "point": {"lng": -35.8100845036077, "lat": -9.576322243850095}, "size": 2, "preparation": 6, "time": 23, "timestamp": 96}, {"id": "ad14443866aad1414269f8659278c29a", "point": {"lng": -35.8087513921921, "lat": -9.57888225180626}, "size": 6, "preparation": 5, "time": 39, "timestamp": 149}, {"id": "9a481e5f4f2dac21f106b3906f7b9017", "point": {"lng": -35.76579747377186, "lat": -9.589094237262676}, "size": 1, "preparation": 6, "time": 34, "timestamp": 276}, {"id": "d6f43422397a204f62067ca858cf78b4", "point": {"lng": -35.76633165703686, "lat": -9.589204751945694}, "size": 1, "preparation": 7, "time": 50, "timestamp": 159}, {"id": "ead911d987eb47b366e974140e8010c0", "point": {"lng": -35.77947646230768, "lat": -9.580273138647998}, "size": 7, "preparation": 11, "time": 35, "timestamp": 194}, {"id": "2b5c695ff4b94250e981d0bc86b25759", "point": {"lng": -35.780490467738645, "lat": -9.578207342827579}, "size": 4, "preparation": 11, "time": 39, "timestamp": 321}, {"id": "db37fea79fd9fe6ceb63a15ffedfadeb", "point": {"lng": -35.77978052319835, "lat": -9.579566197110474}, "size": 9, "preparation": 11, "time": 51, "timestamp": 98}, {"id": "55c04f8163dabe8d629e947b62825807", "point": {"lng": -35.77861481736051, "lat": -9.57791611523003}, "size": 9, "preparation": 2, "time": 50, "timestamp": 135}, {"id": "cb9f9d9f8a0e392b0ffa79a4e091f8be", "point": {"lng": -35.779895694997364, "lat": -9.577740387714977}, "size": 4, "preparation": 7, "time": 26, "timestamp": 333}, {"id": "b12650354123a01ffd03db06c295b2a", "point": {"lng": -35.778247953233354, "lat": -9.577584654394249}, "size": 10, "preparation": 14, "time": 47, "timestamp": 159}, {"id": "b0abe01b1455c6a02be58596c857af67", "point": {"lng": -35.73016858742169, "lat": -9.576208215728354}, "size": 10, "preparation": 13, "time": 41, "timestamp": 11}, {"id": "e68cf814c7f8fab45da69afc320d3ec2", "point": {"lng": -35.731127905366215, "lat": -9.568392604921808}, "size": 10, "preparation": 5, "time": 42, "timestamp": 117}, {"id": "780c3fbefac4679f4572970e210b6663", "point": {"lng": -35.732023140086625, "lat": -9.573776953322783}, "size": 1, "preparation": 5, "time": 51, "timestamp": 305}, {"id": "3bba29dc2cb7806a8d19e4090aae6b5", "point": {"lng": -35.72923810264407, "lat": -9.571258622437346}, "size": 5, "preparation": 10, "time": 31, "timestamp": 131}, {"id": "6003a0936286aaad922a28c8d6d0fd6c", "point": {"lng": -35.751936518818766, "lat": -9.55264067261251}, "size": 1, "preparation": 12, "time": 48, "timestamp": 295}, {"id": "80cd360f26d11170d7886bd8a1fa69e4", "point": {"lng": -35.75489839829893, "lat": -9.55223936431595}, "size": 5, "preparation": 14, "time": 26, "timestamp": 96}, {"id": "d06bad7c31c572d554af12ba0c4df3d6", "point": {"lng": -35.75797073970383, "lat": -9.550912338305702}, "size": 8, "preparation": 11, "time": 37, "timestamp": 305}, {"id": "e68b9e1e77f22122386954ea44c340f1", "point": {"lng": -35.76027925813703, "lat": -9.54861387055464}, "size": 9, "preparation": 11, "time": 46, "timestamp": 353}, {"id": "b9383c0afec47241a2fbbff8e30279c3", "point": {"lng": -35.75543044846301, "lat": -9.55001033244461}, "size": 1, "preparation": 15, "time": 48, "timestamp": 321}, {"id": "6089053e32bbeabad4174ba75a1b3b5", "point": {"lng": -35.75780729979119, "lat": -9.551039413821915}, "size": 3, "preparation": 14, "time": 25, "timestamp": 166}, {"id": "f1fe6dd310f4da505a8b29b15db079c6", "point": {"lng": -35.75374362662252, "lat": -9.55418512439502}, "size": 5, "preparation": 2, "time": 31, "timestamp": 112}, {"id": "4b0a31a072413687e8195409073ad826", "point": {"lng": -35.75259373889317, "lat": -9.553934816721743}, "size": 4, "preparation": 11, "time": 24, "timestamp": 69}, {"id": "aa3c88d1ec54bd852eaff12d6542c73e", "point": {"lng": -35.758450145480396, "lat": -9.550796719044195}, "size": 4, "preparation": 5, "time": 25, "timestamp": 194}, {"id": "167666fde9028e854524fb6e7849dd4c", "point": {"lng": -35.75482922439833, "lat": -9.548964200735192}, "size": 1, "preparation": 5, "time": 24, "timestamp": 324}, {"id": "54d92cefe332e053b54db17edc615f4d", "point": {"lng": -35.72849536524004, "lat": -9.539992273300525}, "size": 9, "preparation": 11, "time": 29, "timestamp": 51}, {"id": "77b1979ba03480db42827be81766f5fd", "point": {"lng": -35.72720353211509, "lat": -9.545121828100125}, "size": 2, "preparation": 5, "time": 52, "timestamp": 192}, {"id": "6e75aae846be08cbbd7f1809c85ae22f", "point": {"lng": -35.76928999835007, "lat": -9.576948223696714}, "size": 3, "preparation": 12, "time": 52, "timestamp": 9}, {"id": "2b28dd03cc72d79a36ad03fcd2b5ac98", "point": {"lng": -35.752332392460666, "lat": -9.576345872169876}, "size": 1, "preparation": 12, "time": 35, "timestamp": 37}, {"id": "d4270910bbcb96d13bd97ad07eae0563", "point": {"lng": -35.75175460974019, "lat": -9.577405360424265}, "size": 7, "preparation": 15, "time": 33, "timestamp": 132}, {"id": "b5a2f3d4bae934e5f0b428b9b423b9ab", "point": {"lng": -35.74816497623832, "lat": -9.579734411345797}, "size": 4, "preparation": 11, "time": 36, "timestamp": 248}, {"id": "1424b857b20350f74287a8a1fcc85425", "point": {"lng": -35.751761149939675, "lat": -9.575623161673342}, "size": 7, "preparation": 15, "time": 27, "timestamp": 228}, {"id": "54c0f8a004b54b1acd71af1449af6b4", "point": {"lng": -35.784201008945715, "lat": -9.574351216539288}, "size": 7, "preparation": 14, "time": 39, "timestamp": 205}, {"id": "610376d75892d0b7d27c730e50121f39", "point": {"lng": -35.78496173926961, "lat": -9.578512169370166}, "size": 7, "preparation": 10, "time": 33, "timestamp": 169}, {"id": "55a3dce0f1e4cb84822c6fdd6d914388", "point": {"lng": -35.78791065150251, "lat": -9.571509395888}, "size": 2, "preparation": 7, "time": 34, "timestamp": 49}, {"id": "7f12fba85e0934e24f49105981544018", "point": {"lng": -35.75577109527332, "lat": -9.560972208889746}, "size": 7, "preparation": 4, "time": 22, "timestamp": 47}, {"id": "98636b81d7de62a4a69a6a284cc167d9", "point": {"lng": -35.75522550292824, "lat": -9.561113814298139}, "size": 4, "preparation": 14, "time": 38, "timestamp": 118}, {"id": "c72129d9a297cdefd476700301bc2e3", "point": {"lng": -35.75625307347837, "lat": -9.561401730895474}, "size": 5, "preparation": 12, "time": 51, "timestamp": 16}, {"id": "300e23d2db50fad0d0950e0ce69e6ec", "point": {"lng": -35.76340496617955, "lat": -9.584411208966474}, "size": 6, "preparation": 12, "time": 23, "timestamp": 48}, {"id": "aeb864276e1032f2e7a29a260234637d", "point": {"lng": -35.75637025309061, "lat": -9.542136183448877}, "size": 2, "preparation": 4, "time": 34, "timestamp": 317}, {"id": "92074d6bdca2073625f82a44363897bb", "point": {"lng": -35.75978438296584, "lat": -9.539446508845385}, "size": 8, "preparation": 2, "time": 45, "timestamp": 239}, {"id": "9ee6cd41357286aed91dc9502baad1c2", "point": {"lng": -35.764282372012026, "lat": -9.5408903526348}, "size": 2, "preparation": 4, "time": 44, "timestamp": 278}, {"id": "c0167be793da775cd989feb859ed29eb", "point": {"lng": -35.761364668523285, "lat": -9.541984267930582}, "size": 3, "preparation": 2, "time": 43, "timestamp": 6}, {"id": "4e4842146709fc715d0a95e4e2d8dc1a", "point": {"lng": -35.780835232002765, "lat": -9.550707342602674}, "size": 7, "preparation": 5, "time": 47, "timestamp": 226}, {"id": "4b31f3772dc897601c3c73f05cfa5b51", "point": {"lng": -35.77348179903159, "lat": -9.553822613878149}, "size": 7, "preparation": 6, "time": 46, "timestamp": 290}, {"id": "d8aa37836d14857112c6ff8a5f4aa22b", "point": {"lng": -35.78809790552917, "lat": -9.527958528603644}, "size": 3, "preparation": 9, "time": 23, "timestamp": 347}, {"id": "739853932fda9040b2f4611a8c0ed0d3", "point": {"lng": -35.748011555819716, "lat": -9.565774916026232}, "size": 8, "preparation": 3, "time": 30, "timestamp": 315}, {"id": "d0586aca38e4309342dcfcd68948c04b", "point": {"lng": -35.74287963291203, "lat": -9.569177660858}, "size": 8, "preparation": 10, "time": 24, "timestamp": 43}, {"id": "7f1595a1d264886b0c3200013688dfff", "point": {"lng": -35.735450687454005, "lat": -9.586490624148416}, "size": 3, "preparation": 13, "time": 52, "timestamp": 41}, {"id": "ea6f65648cc57147696d48b1345d1312", "point": {"lng": -35.73799383403823, "lat": -9.58259580457812}, "size": 7, "preparation": 3, "time": 51, "timestamp": 222}, {"id": "3a293ff0e149d36269950384be20652e", "point": {"lng": -35.74291332514905, "lat": -9.584468512474421}, "size": 4, "preparation": 2, "time": 27, "timestamp": 267}, {"id": "423218b17fcca98d956020ca3e22c429", "point": {"lng": -35.776937324482184, "lat": -9.569657107734825}, "size": 10, "preparation": 14, "time": 45, "timestamp": 9}, {"id": "cbd4bb7690b06b6d19dfb93fe91adc12", "point": {"lng": -35.77780309871972, "lat": -9.57152852608553}, "size": 2, "preparation": 13, "time": 51, "timestamp": 349}, {"id": "1801ed28eacc5ab53e85f4a451f83815", "point": {"lng": -35.78214707763861, "lat": -9.55966106276443}, "size": 6, "preparation": 1, "time": 46, "timestamp": 306}, {"id": "882e7bae4f7722723d9db54bee8b3ddf", "point": {"lng": -35.78453277254943, "lat": -9.590975090540857}, "size": 5, "preparation": 6, "time": 47, "timestamp": 226}, {"id": "737a818399672b5591a29246315b4a87", "point": {"lng": -35.778336035042464, "lat": -9.590237699124673}, "size": 4, "preparation": 1, "time": 45, "timestamp": 181}, {"id": "d72e92b090d7efacb44b532cfeb7e4b4", "point": {"lng": -35.78686111475064, "lat": -9.54682351305915}, "size": 4, "preparation": 14, "time": 50, "timestamp": 343}, {"id": "b94d48a4c5a917f073a62893f0a4c565", "point": {"lng": -35.7659913484421, "lat": -9.56913619276124}, "size": 1, "preparation": 11, "time": 33, "timestamp": 346}, {"id": "7dbf262ceda47a86a50ed1e152bc75cd", "point": {"lng": -35.76499360028306, "lat": -9.568350683840784}, "size": 6, "preparation": 13, "time": 47, "timestamp": 248}, {"id": "7dbf262ceda47a86a50ed1e152bc75cd", "point": {"lng": -35.76499360028306, "lat": -9.568350683840784}, "size": 6, "preparation": 13, "time": 47, "timestamp": 248}, {"id": "b2cff2741e45e559b54f256e7a100100", "point": {"lng": -35.76414355751443, "lat": -9.567375612910775}, "size": 6, "preparation": 14, "time": 40, "timestamp": 294}, {"id": "48850efcc31c637b18f1f02f4f8325b9", "point": {"lng": -35.73088596636292, "lat": -9.561802032003053}, "size": 4, "preparation": 6, "time": 38, "timestamp": 27}, {"id": "18e8acaeefb7e8ef9be5a3dbf85cfaf3", "point": {"lng": -35.75928824929926, "lat": -9.555821744273889}, "size": 7, "preparation": 11, "time": 37, "timestamp": 154}, {"id": "a33c049d226b9de0ee2b4023b247a79a", "point": {"lng": -35.7642275788221, "lat": -9.553636836087872}, "size": 5, "preparation": 14, "time": 44, "timestamp": 292}, {"id": "40c2c25237bdb273a6e02b0a69bfbf13", "point": {"lng": -35.76506046442706, "lat": -9.558285107773715}, "size": 5, "preparation": 1, "time": 38, "timestamp": 71}, {"id": "bf6b5d802a30aacb01644de8e7e56e46", "point": {"lng": -35.76408674774357, "lat": -9.557271322489811}, "size": 3, "preparation": 12, "time": 38, "timestamp": 14}, {"id": "ea859307a96e418adff1b7de9f5fa7", "point": {"lng": -35.777621685522305, "lat": -9.579579228328473}, "size": 7, "preparation": 7, "time": 33, "timestamp": 58}, {"id": "648d5c1ac24ec78f2f968760355c5535", "point": {"lng": -35.77481379486006, "lat": -9.579978341534886}, "size": 1, "preparation": 4, "time": 39, "timestamp": 357}, {"id": "814992614eebdb4046ad3607ce9a877f", "point": {"lng": -35.72665155005121, "lat": -9.595060824307298}, "size": 5, "preparation": 3, "time": 37, "timestamp": 116}, {"id": "a36b587f08cf07bf20ae6759091fd733", "point": {"lng": -35.72945338269128, "lat": -9.596527112450442}, "size": 7, "preparation": 7, "time": 30, "timestamp": 57}, {"id": "c8f50a21d7091caf26e866e3ac6fa7bd", "point": {"lng": -35.742888260258404, "lat": -9.56127201902586}, "size": 2, "preparation": 8, "time": 48, "timestamp": 356}, {"id": "c9a22eca4043f363fb322714a732fb4", "point": {"lng": -35.741386975691505, "lat": -9.560303408874598}, "size": 2, "preparation": 12, "time": 39, "timestamp": 189}, {"id": "4a3adfa25edda1343b64ff3666d81f21", "point": {"lng": -35.741995287951354, "lat": -9.562025676246318}, "size": 3, "preparation": 7, "time": 29, "timestamp": 206}, {"id": "bca4e57f59ea976ab286cad392bb0754", "point": {"lng": -35.74268917144194, "lat": -9.560625158120356}, "size": 5, "preparation": 10, "time": 45, "timestamp": 95}, {"id": "f45b4d229820286d14bcebff3c555d80", "point": {"lng": -35.76283451851555, "lat": -9.578184617576218}, "size": 5, "preparation": 15, "time": 35, "timestamp": 11}, {"id": "bb964e4ce7ca782dce44c2f8f6c10ed1", "point": {"lng": -35.76396956105241, "lat": -9.577364898673165}, "size": 5, "preparation": 3, "time": 33, "timestamp": 278}, {"id": "565bd61822e9e590898d980f28b60a5a", "point": {"lng": -35.761459643658355, "lat": -9.577950896658251}, "size": 1, "preparation": 1, "time": 36, "timestamp": 173}, {"id": "a4113ca51eaacb13df48bd6f73481b54", "point": {"lng": -35.758214482380744, "lat": -9.578052317557306}, "size": 1, "preparation": 7, "time": 43, "timestamp": 29}, {"id": "7a92299fde211f57285ba579d3d6264e", "point": {"lng": -35.72108119710444, "lat": -9.549371996512686}, "size": 9, "preparation": 5, "time": 44, "timestamp": 242}, {"id": "9be1eded537848d1ae34878888792914", "point": {"lng": -35.72087560081901, "lat": -9.546550579519486}, "size": 2, "preparation": 3, "time": 38, "timestamp": 86}, {"id": "adb877e7cbe9a07a2422a761c24791dc", "point": {"lng": -35.719973079162685, "lat": -9.54840817432271}, "size": 2, "preparation": 4, "time": 47, "timestamp": 301}, {"id": "4d4cea80d06fbe163bef68bb6e0b59e9", "point": {"lng": -35.72345587925457, "lat": -9.551757887311224}, "size": 10, "preparation": 2, "time": 44, "timestamp": 106}, {"id": "44c1da7785ce0d384f84bdc1c825284a", "point": {"lng": -35.725924354779714, "lat": -9.548959943478332}, "size": 6, "preparation": 12, "time": 43, "timestamp": 37}, {"id": "8f3a509074809f7205aa6f21edadc40b", "point": {"lng": -35.750934687721895, "lat": -9.583096235799541}, "size": 10, "preparation": 9, "time": 40, "timestamp": 264}, {"id": "b48347875e17b71edb25fc09b52310c9", "point": {"lng": -35.756508336467235, "lat": -9.576657315250044}, "size": 3, "preparation": 9, "time": 38, "timestamp": 151}, {"id": "e682f8dca74187c02a2567f3542a8d26", "point": {"lng": -35.75104563475427, "lat": -9.541068091867432}, "size": 2, "preparation": 15, "time": 23, "timestamp": 51}, {"id": "61b6afbc14ad98f82e1b482a6283f8de", "point": {"lng": -35.73976802608669, "lat": -9.57927113924727}, "size": 5, "preparation": 4, "time": 48, "timestamp": 285}, {"id": "4b3f3e5611505544cb170c474e23fd0d", "point": {"lng": -35.73999169627653, "lat": -9.571217057167882}, "size": 4, "preparation": 12, "time": 25, "timestamp": 161}, {"id": "3f8bea3aed21478e8e9f1fb2d67183e0", "point": {"lng": -35.73807652521429, "lat": -9.575206632484544}, "size": 6, "preparation": 4, "time": 47, "timestamp": 71}, {"id": "f5dc0e3e9c2dc323250bf8b4d95fb5b5", "point": {"lng": -35.73868607021354, "lat": -9.580883687530747}, "size": 9, "preparation": 11, "time": 32, "timestamp": 273}]}